adlitteratim/__init__.py
adlitteratim/cli.py
adlitteratim-0.0.1.dist-info/licenses/LICENSE
adlitteratim-0.0.1.dist-info/METADATA
adlitteratim-0.0.1.dist-info/WHEEL
adlitteratim-0.0.1.dist-info/entry_points.txt
adlitteratim-0.0.1.dist-info/top_level.txt
adlitteratim-0.0.1.dist-info/RECORD
