Metadata-Version: 2.4
Name: adlitteratim
Version: 0.0.1
Summary: CLI tool to manage and test your LLM prompts ad litteratim.
Requires-Python: >=3.8
License-File: LICENSE
Requires-Dist: click
Requires-Dist: ruamel.yaml
Dynamic: license-file
